{
    "url": "https://www.agenciaminas.mg.gov.br/noticia/rede-minas-exibe-superliga-de-volei-a-partir-desta-quinta-feira-9-1",
    "titulo": "Rede Minas exibe Superliga de Vôlei a partir desta quinta-feira (9/1)",
    "descricao": "A Rede Minas dá mais um passo marcante na transmissão de jogos de vôlei e traz as partidas do segundo turno da Superliga, das categorias masculina...",
    "temas": [
        "Esportes"
    ],
    "imagem": "https://www.agenciaminas.mg.gov.br/system/news/images/000/124/785/original/Praia_Clube_e_Sada_Cruzeiro_-_cr%C3%A9dito_Bruno_Cunha_Praia_Clube_%283%29.jpg?1736349171",
    "data": null,
    "texto": ""
}