{
    "url": "https://www.agenciaminas.mg.gov.br/noticia/sete-municipios-sediam-partidas-nesta-edicao-de-retomada-dos-jogos-do-interior-de-minas",
    "titulo": "Sete municípios sediam partidas nesta edição de retomada dos Jogos do Interior de Minas",
    "descricao": "A Etapa Microrregional dos Jogos do Interior de Minas (Jimi) Futsal teve início na terça-feira (30/4). Até o dia 5/5, equipes masculinas e...",
    "temas": [
        "Social",
        "Esportes"
    ],
    "imagem": "https://www.agenciaminas.mg.gov.br/system/news/images/000/121/894/original/JIMI.jpg?1714664548",
    "data": null,
    "texto": ""
}